tokenhmac/__init__.py
tokenhmac/token.py
tokenhmac-1.0.0.dist-info/LICENSE
tokenhmac-1.0.0.dist-info/METADATA
tokenhmac-1.0.0.dist-info/WHEEL
tokenhmac-1.0.0.dist-info/top_level.txt
tokenhmac-1.0.0.dist-info/RECORD
