Metadata-Version: 2.1
Name: tokenhmac
Version: 1.0.0
Summary: Fast JWT
Home-page: https://github.com/v-v-vishnevskiy/tokenhmac
Author: Valery Vishnevskiy
Author-email: v.v.vishnevskiy@yandex.ru
License: MIT
Project-URL: GitHub: repo, https://github.com/v-v-vishnevskiy/tokenhmac
Keywords: jwt,token,HMAC,HS256,HS384,HS512,encryption
Platform: UNKNOWN
Classifier: Operating System :: Unix
Classifier: Programming Language :: Python
Classifier: Programming Language :: Python :: 3
Provides: tokenhmac
